oscalling/__init__.py
oscalling/core.py
oscalling/env.py
oscalling/fs.py
oscalling/hardware.py
oscalling/memory.py
oscalling/process.py
oscalling-2.0.0.dist-info/LICENSE
oscalling-2.0.0.dist-info/METADATA
oscalling-2.0.0.dist-info/WHEEL
oscalling-2.0.0.dist-info/top_level.txt
oscalling-2.0.0.dist-info/RECORD
