Metadata-Version: 2.1
Name: oscalling
Version: 2.0.0
Summary: A powerful, unified OS manipulation package with built-in memory and hardware management.
Author-email: "Rheehose (Rhee Creative)" <rheehose@example.com>
License: MIT License
Project-URL: Homepage, https://github.com/rheehose/oscalling
Project-URL: Repository, https://github.com/rheehose/oscalling
Project-URL: Issues, https://github.com/rheehose/oscalling/issues
Keywords: os,system,memory-management,hardware,process,automation,utilities
Classifier: Development Status :: 5 - Production/Stable
Classifier: Intended Audience :: Developers
Classifier: License :: OSI Approved :: MIT License
Classifier: Operating System :: OS Independent
Classifier: Programming Language :: Python :: 3
Classifier: Programming Language :: Python :: 3.7
Classifier: Programming Language :: Python :: 3.8
Classifier: Programming Language :: Python :: 3.9
Classifier: Programming Language :: Python :: 3.10
Classifier: Programming Language :: Python :: 3.11
Classifier: Programming Language :: Python :: 3.12
Classifier: Topic :: System :: Operating System
Classifier: Topic :: System :: Systems Administration
Requires-Python: >=3.7
License-File: LICENSE
Requires-Dist: psutil >=5.0.0
